README.md
bump.py
cgse-2025.0.9.dist-info/METADATA
cgse-2025.0.9.dist-info/WHEEL
cgse-2025.0.9.dist-info/RECORD
