Metadata-Version: 2.4
Name: cgse
Version: 2025.0.9
Summary: Generic Common-EGSE: Commanding and monitoring lab equipment
Author-email: Rik Huygen <rik.huygen@kuleuven.be>, Sara Regibo <sara.regibo@kuleuven.be>
License: MIT
Requires-Python: >=3.9
Requires-Dist: rich>=13.9.4
Requires-Dist: tomlkit>=0.13.2
